{
  "updated": "2026-07-14T15:01:03.148Z",
  "alerts": [
    {
      "ticker": "OSS",
      "changePct": 8.6913,
      "flaggedAt": "2026-07-14T15:01:03.148Z"
    },
    {
      "ticker": "ARM",
      "changePct": -7.5451,
      "flaggedAt": "2026-07-14T15:01:03.148Z"
    },
    {
      "ticker": "IQMX",
      "changePct": 6.1111,
      "flaggedAt": "2026-07-14T15:01:03.148Z"
    },
    {
      "ticker": "XNDU",
      "changePct": 5.5238,
      "flaggedAt": "2026-07-14T15:01:03.148Z"
    },
    {
      "ticker": "OUST",
      "changePct": 5.4084,
      "flaggedAt": "2026-07-14T15:01:03.148Z"
    },
    {
      "ticker": "ALMU",
      "changePct": 5.0555,
      "flaggedAt": "2026-07-14T15:01:03.148Z"
    },
    {
      "ticker": "PENG",
      "changePct": -5.0253,
      "flaggedAt": "2026-07-14T15:01:03.148Z"
    }
  ]
}
