{
  "updated": "2026-07-22T18:19:45.670Z",
  "quotes": {
    "ALMU": {
      "price": 16.01,
      "changePct": -2.497
    },
    "ANET": {
      "price": 175.27,
      "changePct": 0.3952
    },
    "ARM": {
      "price": 284.75,
      "changePct": -1.7188
    },
    "ASTS": {
      "price": 62.245,
      "changePct": -1.7288
    },
    "BRUN": {
      "price": 30.54,
      "changePct": 2.363
    },
    "CIFR": {
      "price": 23.705,
      "changePct": 3.5605
    },
    "CRDO": {
      "price": 228.585,
      "changePct": 2.1061
    },
    "EUV": {
      "price": 27.49,
      "changePct": 5.4469
    },
    "LPKFF": {
      "price": 19.17,
      "changePct": -0.7764
    },
    "LUMN": {
      "price": 6.675,
      "changePct": -1.2574
    },
    "MU": {
      "price": 969.26,
      "changePct": -0.1607
    },
    "NBIS": {
      "price": 224.01,
      "changePct": 3.2685
    },
    "NOK": {
      "price": 10.395,
      "changePct": -2.2107
    },
    "OSS": {
      "price": 13.325,
      "changePct": -4.2744
    },
    "OUST": {
      "price": 39.655,
      "changePct": -2.5197
    },
    "PENG": {
      "price": 59.415,
      "changePct": 2.2633
    },
    "RAAQ": {
      "price": 13.42,
      "changePct": 0
    },
    "RKLB": {
      "price": 70.445,
      "changePct": 1.917
    },
    "SILC": {
      "price": 44.85,
      "changePct": -4.1667
    },
    "SMH": {
      "price": 611.51,
      "changePct": 3.1214
    },
    "TEM": {
      "price": 61.55,
      "changePct": 7.4734
    },
    "WYFI": {
      "price": 39.135,
      "changePct": 6.5188
    },
    "WYY": {
      "price": 11.1,
      "changePct": -8.4913
    },
    "XNDU": {
      "price": 11.099,
      "changePct": 1.6392
    },
    "IQMX": {
      "price": 11.64,
      "changePct": -2.5941
    },
    "SPY": {
      "price": 748.24,
      "changePct": -0.0053
    }
  }
}
